LICENSE
MANIFEST.in
README.rst
setup.py
pyleus/__init__.py
pyleus/_base_jar.py
pyleus/compat.py
pyleus/configuration.py
pyleus/exception.py
pyleus/json_fields_bolt.py
pyleus/pyleus-base.jar
pyleus/testing.py
pyleus/utils.py
pyleus.egg-info/PKG-INFO
pyleus.egg-info/SOURCES.txt
pyleus.egg-info/dependency_links.txt
pyleus.egg-info/requires.txt
pyleus.egg-info/top_level.txt
pyleus/cli/__init__.py
pyleus/cli/build.py
pyleus/cli/cli.py
pyleus/cli/storm_cluster.py
pyleus/cli/topologies.py
pyleus/cli/topology_spec.py
pyleus/cli/virtualenv_proxy.py
pyleus/cli/commands/__init__.py
pyleus/cli/commands/build_subcommand.py
pyleus/cli/commands/kill_subcommand.py
pyleus/cli/commands/list_subcommand.py
pyleus/cli/commands/local_subcommand.py
pyleus/cli/commands/run_subcommand.py
pyleus/cli/commands/subcommand.py
pyleus/cli/commands/submit_subcommand.py
pyleus/storm/__init__.py
pyleus/storm/bolt.py
pyleus/storm/component.py
pyleus/storm/spout.py
pyleus/storm/serializers/__init__.py
pyleus/storm/serializers/json_serializer.py
pyleus/storm/serializers/msgpack_serializer.py
pyleus/storm/serializers/serializer.py
scripts/pyleus