Metadata-Version: 1.0
Name: pyleus
Version: 0.2.4
Summary: Standard library and deployment tools for using Python with Storm
Home-page: http://pyleus.org
Author: Patrick Lucas
Author-email: plucas@yelp.com
License: UNKNOWN
Platform: UNKNOWN
Classifier: Programming Language :: Python
Classifier: Programming Language :: Python :: 2.6
Classifier: Programming Language :: Python :: 2.7
Classifier: Operating System :: OS Independent
Classifier: License :: OSI Approved :: Apache Software License
Classifier: Intended Audience :: Developers
Classifier: Topic :: Software Development :: Libraries
Classifier: Topic :: System :: Distributed Computing
Classifier: Development Status :: 4 - Beta
